Metadata-Version: 1.0
Name: aide-tutorial
Version: 0.0.0
Summary: aide_tutorial
Home-page: UNKNOWN
Author: AguaClara
Author-email: aguaclara@cornell.edu
License: Apache License (2.0)
Platform: UNKNOWN
